enhancedmath/__init__.py
enhancedmath/array.py
enhancedmath/constants.py
enhancedmath/factorial.py
enhancedmath/func.py
enhancedmath/advanced/__init__.py
enhancedmath/advanced/polynomial.py
enhancedmath/advanced/radicals.py
enhancedmath/advanced/slope.py
enhancedmath-0.2.1.dist-info/METADATA
enhancedmath-0.2.1.dist-info/WHEEL
enhancedmath-0.2.1.dist-info/top_level.txt
enhancedmath-0.2.1.dist-info/RECORD
