Metadata-Version: 2.1
Name: enhancedmath
Version: 0.2.1
Summary: Expanded and Enhanced Math Package
Home-page: https://enhancedmathdocs.limegradient.repl.co/
Author: Lime_Gradient
Author-email: limegradientyt@gmail.com
License: MIT
Platform: UNKNOWN
Requires-Dist: numpy
Requires-Dist: scipy
